{
    "transactions": [
        {
            "recipientId": "P8nnStMyikL35ht19gNouJYnW5RPPZVMFi",
            "amount": 10091100635
        },
        {
            "recipientId": "P93mS5ZVPRRip8XefTU3NvCwHFsoi2Fq8y",
            "amount": 1772509506
        },
        {
            "recipientId": "PAQJFYe1eAsm3SKKY1WW128ZkMj3C3WPgA",
            "amount": 47517067497
        },
        {
            "recipientId": "PB23uc6eBBgoBtHv2fDDvEBrCZJfckfCVZ",
            "amount": 213444176986
        },
        {
            "recipientId": "PDAh1CK3cJScGYFF9PsCUWAJMCeXwziVLK",
            "amount": 110354199219
        },
        {
            "recipientId": "PEoBQqGCEyQFqGKuaQ7ZwKZuDnQLMsykSy",
            "amount": 12953731078
        },
        {
            "recipientId": "PHn61Zt746VXC19eCiu2UmVfyx34jbFo7g",
            "amount": 135692984819
        },
        {
            "recipientId": "PHZkNqEQf7LQQAjMqZK6mcZxsQxKcYkUTU",
            "amount": 32924841369
        },
        {
            "recipientId": "PPRmE8hGbHAg5nmsk9js1oC3uiwVdHwwR6",
            "amount": 5673851937
        },
        {
            "recipientId": "PSVypUsv6dTG6o81oTsUb3RUdBw3uDzndn",
            "amount": 401366660251
        },
        {
            "recipientId": "PSy5SnVi6b3vjBeb9e8FYhrWc7KNk9ixER",
            "amount": 1426106117338
        },
        {
            "recipientId": "PUpVvkXqsZpQxKkYueYVE3vzTvEsTNgpSs",
            "amount": 2636644028
        },
        {
            "recipientId": "PWbEazG9bGaHMQp7Zx4Lks7WoiuUcjnpkU",
            "amount": 3471305160
        },
        {
            "recipientId": "PX11A6qnVDK5EfDnhEyxSVtF5hfhdB9Mea",
            "amount": 29515162588
        },
        {
            "recipientId": "PLytEzkAvhjtr5Ku6y79EKK3sKKWy7ReQY",
            "amount": 71494999
        },
        {
            "recipientId": "PLGEyYu3LZ6tGRQwWweT2wsVzBsgGBYJWW",
            "amount": 280778455418
        }
    ],
    "transactionsPending": [],
    "donations": [],
    "donationsPercentage": [
        {
            "recipientId": "PEu66GuDC65aAJaGU99fGNZ5jxH9wS5ivM",
            "amount": 67860000000
        }
    ]
}