{
    "transactions": [
        {
            "recipientId": "PCDtfR9YTd6SMJbtJuKnSQiwMh2Q22ZH8c",
            "amount": 185339129888
        },
        {
            "recipientId": "PCM9qCUmo8TtRawHB8iZc5rVJ6RVZcHEWW",
            "amount": 50420305189
        },
        {
            "recipientId": "PGqUjs3PnsRfRmGrgCAtDq128KcUBumuee",
            "amount": 17546689636
        },
        {
            "recipientId": "PNncWRNVoaAX8y9grBjrhtPwUtHhLnQAtJ",
            "amount": 11379950342
        },
        {
            "recipientId": "PKyaDLTBG6rW3qXxiDyDryicmFfnM1SMBQ",
            "amount": 238082865945
        },
        {
            "recipientId": "PDWCcCW8QkHw6AGM3RfCobPRcupakSmN7C",
            "amount": 27403403562
        },
        {
            "recipientId": "PHFT4nmHJ6SpW2BX3BKkkqFpD8LBbnca4Q",
            "amount": 555232945730
        },
        {
            "recipientId": "PPkqx5a5SM6ChuxGckVfodHtCRNRNJMACK",
            "amount": 350607929320
        },
        {
            "recipientId": "PAXuagsSNU7H1EbaXGCn65A5Bz2egZEjVJ",
            "amount": 540679980804
        },
        {
            "recipientId": "PWwxK13XGHkyoeztdbAGYA1kopNjcBMD9R",
            "amount": 119682798737
        },
        {
            "recipientId": "PGX5sz2AP1y9zABe2m5kBHugQsjDHcXNuB",
            "amount": 168024000842
        }
    ],
    "transactionsPending": [],
    "donations": [],
    "donationsPercentage": [
        {
            "recipientId": "PEu66GuDC65aAJaGU99fGNZ5jxH9wS5ivM",
            "amount": 56610000000
        }
    ]
}